[{
    "id": 1,
    "first_name": "Emile",
    "last_name": "Ackery",
    "email": "eackery0@ameblo.jp",
    "password": "ACHYomtylo7m",
    "category": "Construction Expeditor",
    "image": "http://dummyimage.com/247x100.png/cc0000/ffffff"
  }, {
    "id": 2,
    "first_name": "Rora",
    "last_name": "Charity",
    "email": "rcharity1@fda.gov",
    "password": "5etnXJ2",
    "category": "Engineer",
    "image": "http://dummyimage.com/156x100.png/cc0000/ffffff"
  }, {
    "id": 3,
    "first_name": "Obie",
    "last_name": "Gaenor",
    "email": "ogaenor2@narod.ru",
    "password": "5boopb8l",
    "category": "Supervisor",
    "image": "http://dummyimage.com/107x100.png/5fa2dd/ffffff"
  }, {
    "id": 4,
    "first_name": "Marget",
    "last_name": "Mertel",
    "email": "mmertel3@imdb.com",
    "password": "cx7wNfQ5Fy",
    "category": "Construction Foreman",
    "image": "http://dummyimage.com/190x100.png/ff4444/ffffff"
  }, {
    "id": 5,
    "first_name": "Shelba",
    "last_name": "Almeida",
    "email": "salmeida4@timesonline.co.uk",
    "password": "cDRUyY",
    "category": "Supervisor",
    "image": "http://dummyimage.com/173x100.png/ff4444/ffffff"
  }, {
    "id": 6,
    "first_name": "Joya",
    "last_name": "Viner",
    "email": "jviner5@hhs.gov",
    "password": "YU1OHB2YC",
    "category": "Estimator",
    "image": "http://dummyimage.com/180x100.png/ff4444/ffffff"
  }, {
    "id": 7,
    "first_name": "Clerc",
    "last_name": "Chiddy",
    "email": "cchiddy6@baidu.com",
    "password": "Pij98BNSdYEG",
    "category": "Construction Worker",
    "image": "http://dummyimage.com/109x100.png/5fa2dd/ffffff"
  }, {
    "id": 8,
    "first_name": "Cindra",
    "last_name": "McMurraya",
    "email": "cmcmurraya7@4shared.com",
    "password": "KhpW5w2",
    "category": "Supervisor",
    "image": "http://dummyimage.com/246x100.png/cc0000/ffffff"
  }, {
    "id": 9,
    "first_name": "Griffy",
    "last_name": "Lantaph",
    "email": "glantaph8@nytimes.com",
    "password": "fSqsqC",
    "category": "Project Manager",
    "image": "http://dummyimage.com/238x100.png/ff4444/ffffff"
  }, {
    "id": 10,
    "first_name": "Michelle",
    "last_name": "Condie",
    "email": "mcondie9@microsoft.com",
    "password": "c14sqKRaxJ",
    "category": "Project Manager",
    "image": "http://dummyimage.com/192x100.png/dddddd/000000"
  }]